jp_prefectures_simple/__init__.py
jp_prefectures_simple/cli.py
jp_prefectures_simple/data/jis_x_0401_code.json
jp_prefectures_simple/data/jis_x_0401_name.json
jp_prefectures_simple/prefs.py
jp_prefectures_simple/py.typed
jp_prefectures_simple-0.2.0.dist-info/WHEEL
jp_prefectures_simple-0.2.0.dist-info/METADATA
jp_prefectures_simple-0.2.0.dist-info/RECORD
