Metadata-Version: 2.4
Name: jp_prefectures_simple
Version: 0.2.0
Summary: Japanese prefecture names and JIS X 0401 codes converter.
Keywords: japan,prefecture,jis x 0401,converter
Author: IWAI, Masaharu
Author-email: IWAI, Masaharu <iwaim.sub@gmail.com>
License-Expression: MIT
Classifier: Programming Language :: Python :: 3.10
Classifier: Programming Language :: Python :: 3.11
Classifier: Programming Language :: Python :: 3.12
Classifier: Programming Language :: Python :: 3.13
Classifier: Programming Language :: Python :: 3.14
Classifier: Topic :: Software Development :: Libraries :: Python Modules
Classifier: Topic :: Utilities
Classifier: Intended Audience :: Developers
Classifier: License :: OSI Approved :: MIT License
Classifier: Operating System :: OS Independent
Requires-Python: >=3.10
Project-URL: Documentation, https://github.com/iwaim/jp-prefectures-simple-python
Project-URL: Source, https://github.com/iwaim/jp-prefectures-simple-python
Project-URL: Tracker, https://github.com/iwaim/jp-prefectures-simple-python/issues
